python_compare_ast/__init__.py
python_compare_ast/__main__.py
python_compare_ast-1.0.0.dist-info/LICENSE
python_compare_ast-1.0.0.dist-info/METADATA
python_compare_ast-1.0.0.dist-info/WHEEL
python_compare_ast-1.0.0.dist-info/entry_points.txt
python_compare_ast-1.0.0.dist-info/top_level.txt
python_compare_ast-1.0.0.dist-info/RECORD
