Metadata-Version: 2.1
Name: python-compare-ast
Version: 1.0.0
Summary: Compares ASTs of Python files that have been changed in git
Home-page: https://github.com/omegacen/python-compare-ast
Author: Teake Nutma
License: LGPL-3.0-or-later
Platform: UNKNOWN
Classifier: Programming Language :: Python :: 3
Classifier: License :: OSI Approved :: GNU Lesser General Public License v3 (LGPLv3)
Classifier: Operating System :: OS Independent
Requires-Python: >=3.6
Requires-Dist: gitpython
Requires-Dist: click
Requires-Dist: click-log
